fast_whisper_diarizer/__init__.py
fast_whisper_diarizer/diarizer.py
fast_whisper_diarizer/main.py
fast_whisper_diarizer/transcriber.py
fast_whisper_diarizer/utils.py
fast_whisper_diarizer/config/diar_infer_telephonic.yaml
fast_whisper_diarizer-0.1.32.dist-info/LICENSE
fast_whisper_diarizer-0.1.32.dist-info/METADATA
fast_whisper_diarizer-0.1.32.dist-info/WHEEL
fast_whisper_diarizer-0.1.32.dist-info/entry_points.txt
fast_whisper_diarizer-0.1.32.dist-info/top_level.txt
fast_whisper_diarizer-0.1.32.dist-info/RECORD
