Metadata-Version: 2.1
Name: fast-whisper-diarizer
Version: 0.1.32
Summary: A package for audio transcription and speaker diarization using Whisper and NeMo toolkit
Home-page: https://github.com/salimkt/fast-whisper-diarizer
Author: Salim
Author-email: salimkt25@gmail.com
License: MIT
Classifier: Programming Language :: Python :: 3
Classifier: License :: OSI Approved :: MIT License
Classifier: Operating System :: OS Independent
Requires-Python: >=3.6
License-File: LICENSE
Requires-Dist: faster-whisper==1.1.0
Requires-Dist: ctranslate2==4.4.0
Requires-Dist: nemo-toolkit==2.1.0rc0
Requires-Dist: torch==2.5.1
Requires-Dist: torchaudio==2.5.1
Requires-Dist: omegaconf==2.3.0
Requires-Dist: nltk==3.9.1
Requires-Dist: wget==3.2
Requires-Dist: deepmultilingualpunctuation==1.0.1
Requires-Dist: demucs==4.0.1
Requires-Dist: numpy==1.26.4
Requires-Dist: hydra-core==1.3.2
Requires-Dist: lhotse==1.29.0
Requires-Dist: jiwer
Requires-Dist: webdataset==0.2.100
Requires-Dist: datasets==3.2.0
Requires-Dist: editdistance
Requires-Dist: IPython==8.31.0
Requires-Dist: ctc_forced_aligner
